{
  "name": "JazzCon.Tech",
  "topic": "programming",
  "url": "http://jazzcon.tech/",
  "twitter": "https://twitter.com/jazz_con",
  "city": "New Orleans",
  "stateProvince": "LA",
  "country": "United States",
  "eventStartDate": "2018-03-21T04:00:00.000Z",
  "eventEndDate": "2018-03-23T04:00:00.000Z",
  "cfpStartDate": "2017-09-26T04:00:00.000Z",
  "cfpEndDate": "2017-11-01T04:00:00.000Z",
  "codeOfConduct": "http://jazzcon.tech/",
  "latitude": 29.95106579999999,
  "longitude": -90.0715323,
  "cfpUrl": ""
}